iodict/__init__.py
iodict/meta.py
iodict-0.0.8.dist-info/LICENSE
iodict-0.0.8.dist-info/METADATA
iodict-0.0.8.dist-info/WHEEL
iodict-0.0.8.dist-info/top_level.txt
iodict-0.0.8.dist-info/RECORD
