Metadata-Version: 2.1
Name: iodict
Version: 0.0.8
Summary: A disk backed dictionary implementation.
Home-page: https://github.com/directord/iodict
Author: Kevin Carter
Author-email: kevin@peznauts.com
License: UNKNOWN
Project-URL: Bug Tracker, https://github.com/directord/iodict/issues
Platform: UNKNOWN
Classifier: Development Status :: 5 - Production/Stable
Classifier: Intended Audience :: Information Technology
Classifier: Intended Audience :: System Administrators
Classifier: Intended Audience :: Developers
Classifier: Operating System :: OS Independent
Classifier: Programming Language :: Python :: 3.8
Classifier: Topic :: Utilities
Classifier: Topic :: Software Development :: Libraries :: Python Modules
Requires-Python: >=3.6
License-File: LICENSE
